wxIconSaver.py
wxIconSaver-0.1.7.data/data/share/applications/wxIconSaver.desktop
wxIconSaver-0.1.7.dist-info/LICENSE
wxIconSaver-0.1.7.dist-info/METADATA
wxIconSaver-0.1.7.dist-info/WHEEL
wxIconSaver-0.1.7.dist-info/entry_points.txt
wxIconSaver-0.1.7.dist-info/top_level.txt
wxIconSaver-0.1.7.dist-info/RECORD
